Wallace-8bit/FA.v
module FullAdder(
    input wire a, b, cin,
    output wire sum, cout
);
    assign sum = a ^ b ^ cin;
    assign cout = (a & b) | (a & cin) | (b & cin);
endmodule

Wallace-8bit/CSA.v
module CSA #(parameter N=16)(
    input  wire [N-1:0] A,
    input  wire [N-1:0] B,
    input  wire [N-1:0] D,
    output wire [N-1:0] PS,
    output wire [N-1:0] PC
);
    genvar i;
    generate
        for (i = 0; i < N; i = i + 1) begin : fa_gen
            FullAdder fa_inst (
                .a   (A[i]),
                .b   (B[i]),
                .cin (D[i]),
                .sum (PS[i]),
                .cout(PC[i])
            );
        end
    endgenerate
endmodule

MAC_8bit/booth_encoder.v
module booth_encoder #(
    parameter N_BITS = 16
) (
    input  signed [N_BITS-1:0] multiplicand,
    input  [3:0] group_index,
    input  [2:0] booth_group,
    output reg signed [(2*N_BITS)-1:0] partial_product_out
);

    reg signed [(2*N_BITS)-1:0] unshifted_pp;

    always @(*) begin
        case (booth_group)
            3'b000, 3'b111: unshifted_pp = 0;
            3'b001, 3'b010: unshifted_pp = {{N_BITS{multiplicand[N_BITS-1]}}, multiplicand};
            3'b011:         unshifted_pp = {{(N_BITS-1){multiplicand[N_BITS-1]}}, multiplicand, 1'b0};
            3'b100:         unshifted_pp = -{{(N_BITS-1){multiplicand[N_BITS-1]}}, multiplicand, 1'b0};
            3'b101, 3'b110: unshifted_pp = -{{N_BITS{multiplicand[N_BITS-1]}}, multiplicand};
            default:        unshifted_pp = 0;
        endcase

        // Shift left by 2×group_index
        partial_product_out = (unshifted_pp << (2 * group_index));
    end

endmodule

MAC_8bit/pp_generator.v
module pp_gen (
    input  wire signed [7:0] A,
    input  wire signed [7:0] B,
    output wire signed [4*16-1:0] pp_flat   // 4 partial products × 16 bits each
);

    wire [9:0] B_pad = {B[7], B, 1'b0};  // 8-bit B padded for Booth
    wire signed [15:0] pp [3:0];           // 4 partial products

    genvar i;
    generate
        for (i = 0; i < 4; i = i + 1) begin : booth_stage
            booth_encoder #(.N_BITS(8)) u_booth (
                .multiplicand(A),
                .group_index(i[1:0]),
                .booth_group(B_pad[2*i+2 : 2*i]),
                .partial_product_out(pp[i])
            );
        end
    endgenerate

    assign pp_flat = {pp[3], pp[2], pp[1], pp[0]};
endmodule

Wallace-8bit/top.v
`timescale 1ns/1ps

module booth_wallace_multiplier_seq(
    input  wire clk,
    input  wire rst,
    input  wire en,
    input  wire signed [7:0] A,
    input  wire signed [7:0] B,
    output reg  signed [15:0] P,
    output reg valid
);

    //-----------------------------------------
    // Stage 0: Input Registers
    //-----------------------------------------
    reg signed [7:0] A_reg, B_reg;
    always @(posedge clk or posedge rst) begin
        if (rst) begin
            A_reg <= 0;
            B_reg <= 0;
        end else begin
            A_reg <= A;
            B_reg <= B;
        end
    end

    //-----------------------------------------
    // Stage 1: Partial Product Generation (16-bit each)
    //-----------------------------------------
    wire signed [4*16-1:0] pp_flat_next;
    pp_gen u_pp (.A(A_reg), .B(B_reg), .pp_flat(pp_flat_next));

    reg signed [4*16-1:0] pp_flat_r;
    always @(posedge clk or posedge rst) begin
        if (rst) pp_flat_r <= 0;
        else pp_flat_r <= pp_flat_next;
    end

    wire [15:0] pp [3:0];
    genvar i;
    generate
        for (i=0; i<4; i=i+1) begin : unpack
            assign pp[i] = pp_flat_r[(i+1)*16-1 -: 16];
        end
    endgenerate     
    //-----------------------------------------
    // Stage 2: CSA Layer 1 (4 -> 3)  -- 1 CSA
    //-----------------------------------------
    wire [15:0] s1_sum, s1_carry;
    CSA #(16) csa1 (pp[0], pp[1], pp[2], s1_sum, s1_carry);
    wire [15:0] s1_rem = pp[3];

    reg [15:0] s1_sum_r, s1_carry_r, s1_rem_r;
    always @(posedge clk or posedge rst) begin
        if (rst) begin
            s1_sum_r <= 0; s1_carry_r <= 0; s1_rem_r <= 0;
        end else begin
            s1_sum_r <= s1_sum; s1_carry_r <= s1_carry; s1_rem_r <= s1_rem;
        end
    end

    //-----------------------------------------
    // Stage 3: CSA Layer 2 (3 -> 2)  -- 1 CSA
    //-----------------------------------------
    wire [15:0] s2_sum, s2_carry;
    CSA #(16) csa2 (s1_sum_r, (s1_carry_r << 1), s1_rem_r, s2_sum, s2_carry);

    reg [15:0] s2_sum_r, s2_carry_r;
    always @(posedge clk or posedge rst) begin
        if (rst) begin
            s2_sum_r <= 0; s2_carry_r <= 0;
        end else begin
            s2_sum_r <= s2_sum; s2_carry_r <= s2_carry;
        end
    end

    //-----------------------------------------
    // Stage 4: Final Addition + Output
    //-----------------------------------------
    wire [15:0] P_comb = s2_sum_r + (s2_carry_r << 1);

    always @(posedge clk or posedge rst) begin
        if (rst) begin
            P <= 0;
            valid <= 0;
        end else begin
            P <= P_comb;
            valid <= 1;
        end
    end

endmodule

Wallace-8bit/Wallace_8bit_TB.v
`timescale 1ns/1ps

module Wallace_8bit_TB;

    reg clk;
    reg rst;
    reg en;
    reg signed [7:0] A, B;
    wire signed [15:0] P;
    wire valid;

    booth_wallace_multiplier_seq uut (
        .clk(clk),
        .rst(rst),
        .en(en),
        .A(A),
        .B(B),
        .P(P),
        .valid(valid)
    );

    // Clock
    initial clk = 0;
    always #5 clk = ~clk;

    integer i; // loop variable declared here

    initial begin
        $dumpfile("Wallace_8bit_TB.vcd");
        $dumpvars(0, Wallace_8bit_TB);

        rst = 1; en = 0; A = 0; B = 0;
        #20 rst = 0; en = 1;

        // Fixed test vectors
        A = 8'sd50;  B = 8'sd20;   #20;   // 50 * 20 = 1000
        A = -8'sd10; B = 8'sd12;   #20;   // -10 * 12 = -120
        A = 8'sd100; B = -8'sd5;   #20;   // 100 * -5 = -500
        A = -8'sd128; B = -8'sd1;  #20;   // -128 * -1 = 128
        A = 8'sd127; B = 8'sd127;  #20;   // 127 * 127 = 16129

        // Random tests
         for (i = 0; i < 10; i = i + 1) begin
            A = $random % 256;   // range 0 to 255
            B = $random % 256;
            // convert to signed 8-bit range (-128 to 127)
            if (A > 127) A = A - 256;
            if (B > 127) B = B - 256;
            #20;
        end

        #50;
        $display("Simulation finished");
        $finish;
    end

    initial begin
        $monitor("Time=%0t | A=%d B=%d | P=%d valid=%b", $time, A, B, P, valid);
    end

endmodule

Wallace-8bit/Wallace_8bit_TB.vcd
$date
	Fri Oct 17 12:50:05 2025
$end
$version
	Icarus Verilog
$end
$timescale
	1ps
$end
$scope module Wallace_8bit_TB $end
$var wire 1 ! valid $end
$var wire 16 " P [15:0] $end
$var reg 8 # A [7:0] $end
$var reg 8 $ B [7:0] $end
$var reg 1 % clk $end
$var reg 1 & en $end
$var reg 1 ' rst $end
$var integer 32 ( i [31:0] $end
$scope module uut $end
$var wire 8 ) A [7:0] $end
$var wire 8 * B [7:0] $end
$var wire 1 % clk $end
$var wire 1 & en $end
$var wire 1 ' rst $end
$var wire 16 + s1_rem [15:0] $end
$var wire 16 , s2_sum [15:0] $end
$var wire 16 - s2_carry [15:0] $end
$var wire 16 . s1_sum [15:0] $end
$var wire 16 / s1_carry [15:0] $end
$var wire 64 0 pp_flat_next [63:0] $end
$var wire 16 1 P_comb [15:0] $end
$var reg 8 2 A_reg [7:0] $end
$var reg 8 3 B_reg [7:0] $end
$var reg 16 4 P [15:0] $end
$var reg 64 5 pp_flat_r [63:0] $end
$var reg 16 6 s1_carry_r [15:0] $end
$var reg 16 7 s1_rem_r [15:0] $end
$var reg 16 8 s1_sum_r [15:0] $end
$var reg 16 9 s2_carry_r [15:0] $end
$var reg 16 : s2_sum_r [15:0] $end
$var reg 1 ! valid $end
$scope begin unpack[0] $end
$upscope $end
$scope begin unpack[1] $end
$upscope $end
$scope begin unpack[2] $end
$upscope $end
$scope begin unpack[3] $end
$upscope $end
$scope module csa1 $end
$var wire 16 ; A [15:0] $end
$var wire 16 < B [15:0] $end
$var wire 16 = D [15:0] $end
$var wire 16 > PS [15:0] $end
$var wire 16 ? PC [15:0] $end
$scope begin fa_gen[0] $end
$scope module fa_inst $end
$var wire 1 @ a $end
$var wire 1 A b $end
$var wire 1 B cin $end
$var wire 1 C cout $end
$var wire 1 D sum $end
$upscope $end
$upscope $end
$scope begin fa_gen[1] $end
$scope module fa_inst $end
$var wire 1 E a $end
$var wire 1 F b $end
$var wire 1 G cin $end
$var wire 1 H cout $end
$var wire 1 I sum $end
$upscope $end
$upscope $end
$scope begin fa_gen[2] $end
$scope module fa_inst $end
$var wire 1 J a $end
$var wire 1 K b $end
$var wire 1 L cin $end
$var wire 1 M cout $end
$var wire 1 N sum $end
$upscope $end
$upscope $end
$scope begin fa_gen[3] $end
$scope module fa_inst $end
$var wire 1 O a $end
$var wire 1 P b $end
$var wire 1 Q cin $end
$var wire 1 R cout $end
$var wire 1 S sum $end
$upscope $end
$upscope $end
$scope begin fa_gen[4] $end
$scope module fa_inst $end
$var wire 1 T a $end
$var wire 1 U b $end
$var wire 1 V cin $end
$var wire 1 W cout $end
$var wire 1 X sum $end
$upscope $end
$upscope $end
$scope begin fa_gen[5] $end
$scope module fa_inst $end
$var wire 1 Y a $end
$var wire 1 Z b $end
$var wire 1 [ cin $end
$var wire 1 \ cout $end
$var wire 1 ] sum $end
$upscope $end
$upscope $end
$scope begin fa_gen[6] $end
$scope module fa_inst $end
$var wire 1 ^ a $end
$var wire 1 _ b $end
$var wire 1 ` cin $end
$var wire 1 a cout $end
$var wire 1 b sum $end
$upscope $end
$upscope $end
$scope begin fa_gen[7] $end
$scope module fa_inst $end
$var wire 1 c a $end
$var wire 1 d b $end
$var wire 1 e cin $end
$var wire 1 f cout $end
$var wire 1 g sum $end
$upscope $end
$upscope $end
$scope begin fa_gen[8] $end
$scope module fa_inst $end
$var wire 1 h a $end
$var wire 1 i b $end
$var wire 1 j cin $end
$var wire 1 k cout $end
$var wire 1 l sum $end
$upscope $end
$upscope $end
$scope begin fa_gen[9] $end
$scope module fa_inst $end
$var wire 1 m a $end
$var wire 1 n b $end
$var wire 1 o cin $end
$var wire 1 p cout $end
$var wire 1 q sum $end
$upscope $end
$upscope $end
$scope begin fa_gen[10] $end
$scope module fa_inst $end
$var wire 1 r a $end
$var wire 1 s b $end
$var wire 1 t cin $end
$var wire 1 u cout $end
$var wire 1 v sum $end
$upscope $end
$upscope $end
$scope begin fa_gen[11] $end
$scope module fa_inst $end
$var wire 1 w a $end
$var wire 1 x b $end
$var wire 1 y cin $end
$var wire 1 z cout $end
$var wire 1 { sum $end
$upscope $end
$upscope $end
$scope begin fa_gen[12] $end
$scope module fa_inst $end
$var wire 1 | a $end
$var wire 1 } b $end
$var wire 1 ~ cin $end
$var wire 1 !" cout $end
$var wire 1 "" sum $end
$upscope $end
$upscope $end
$scope begin fa_gen[13] $end
$scope module fa_inst $end
$var wire 1 #" a $end
$var wire 1 $" b $end
$var wire 1 %" cin $end
$var wire 1 &" cout $end
$var wire 1 '" sum $end
$upscope $end
$upscope $end
$scope begin fa_gen[14] $end
$scope module fa_inst $end
$var wire 1 (" a $end
$var wire 1 )" b $end
$var wire 1 *" cin $end
$var wire 1 +" cout $end
$var wire 1 ," sum $end
$upscope $end
$upscope $end
$scope begin fa_gen[15] $end
$scope module fa_inst $end
$var wire 1 -" a $end
$var wire 1 ." b $end
$var wire 1 /" cin $end
$var wire 1 0" cout $end
$var wire 1 1" sum $end
$upscope $end
$upscope $end
$upscope $end
$scope module csa2 $end
$var wire 16 2" A [15:0] $end
$var wire 16 3" B [15:0] $end
$var wire 16 4" D [15:0] $end
$var wire 16 5" PS [15:0] $end
$var wire 16 6" PC [15:0] $end
$scope begin fa_gen[0] $end
$scope module fa_inst $end
$var wire 1 7" a $end
$var wire 1 8" b $end
$var wire 1 9" cin $end
$var wire 1 :" cout $end
$var wire 1 ;" sum $end
$upscope $end
$upscope $end
$scope begin fa_gen[1] $end
$scope module fa_inst $end
$var wire 1 <" a $end
$var wire 1 =" b $end
$var wire 1 >" cin $end
$var wire 1 ?" cout $end
$var wire 1 @" sum $end
$upscope $end
$upscope $end
$scope begin fa_gen[2] $end
$scope module fa_inst $end
$var wire 1 A" a $end
$var wire 1 B" b $end
$var wire 1 C" cin $end
$var wire 1 D" cout $end
$var wire 1 E" sum $end
$upscope $end
$upscope $end
$scope begin fa_gen[3] $end
$scope module fa_inst $end
$var wire 1 F" a $end
$var wire 1 G" b $end
$var wire 1 H" cin $end
$var wire 1 I" cout $end
$var wire 1 J" sum $end
$upscope $end
$upscope $end
$scope begin fa_gen[4] $end
$scope module fa_inst $end
$var wire 1 K" a $end
$var wire 1 L" b $end
$var wire 1 M" cin $end
$var wire 1 N" cout $end
$var wire 1 O" sum $end
$upscope $end
$upscope $end
$scope begin fa_gen[5] $end
$scope module fa_inst $end
$var wire 1 P" a $end
$var wire 1 Q" b $end
$var wire 1 R" cin $end
$var wire 1 S" cout $end
$var wire 1 T" sum $end
$upscope $end
$upscope $end
$scope begin fa_gen[6] $end
$scope module fa_inst $end
$var wire 1 U" a $end
$var wire 1 V" b $end
$var wire 1 W" cin $end
$var wire 1 X" cout $end
$var wire 1 Y" sum $end
$upscope $end
$upscope $end
$scope begin fa_gen[7] $end
$scope module fa_inst $end
$var wire 1 Z" a $end
$var wire 1 [" b $end
$var wire 1 \" cin $end
$var wire 1 ]" cout $end
$var wire 1 ^" sum $end
$upscope $end
$upscope $end
$scope begin fa_gen[8] $end
$scope module fa_inst $end
$var wire 1 _" a $end
$var wire 1 `" b $end
$var wire 1 a" cin $end
$var wire 1 b" cout $end
$var wire 1 c" sum $end
$upscope $end
$upscope $end
$scope begin fa_gen[9] $end
$scope module fa_inst $end
$var wire 1 d" a $end
$var wire 1 e" b $end
$var wire 1 f" cin $end
$var wire 1 g" cout $end
$var wire 1 h" sum $end
$upscope $end
$upscope $end
$scope begin fa_gen[10] $end
$scope module fa_inst $end
$var wire 1 i" a $end
$var wire 1 j" b $end
$var wire 1 k" cin $end
$var wire 1 l" cout $end
$var wire 1 m" sum $end
$upscope $end
$upscope $end
$scope begin fa_gen[11] $end
$scope module fa_inst $end
$var wire 1 n" a $end
$var wire 1 o" b $end
$var wire 1 p" cin $end
$var wire 1 q" cout $end
$var wire 1 r" sum $end
$upscope $end
$upscope $end
$scope begin fa_gen[12] $end
$scope module fa_inst $end
$var wire 1 s" a $end
$var wire 1 t" b $end
$var wire 1 u" cin $end
$var wire 1 v" cout $end
$var wire 1 w" sum $end
$upscope $end
$upscope $end
$scope begin fa_gen[13] $end
$scope module fa_inst $end
$var wire 1 x" a $end
$var wire 1 y" b $end
$var wire 1 z" cin $end
$var wire 1 {" cout $end
$var wire 1 |" sum $end
$upscope $end
$upscope $end
$scope begin fa_gen[14] $end
$scope module fa_inst $end
$var wire 1 }" a $end
$var wire 1 ~" b $end
$var wire 1 !# cin $end
$var wire 1 "# cout $end
$var wire 1 ## sum $end
$upscope $end
$upscope $end
$scope begin fa_gen[15] $end
$scope module fa_inst $end
$var wire 1 $# a $end
$var wire 1 %# b $end
$var wire 1 &# cin $end
$var wire 1 '# cout $end
$var wire 1 (# sum $end
$upscope $end
$upscope $end
$upscope $end
$scope module u_pp $end
$var wire 8 )# A [7:0] $end
$var wire 8 *# B [7:0] $end
$var wire 64 +# pp_flat [63:0] $end
$var wire 10 ,# B_pad [9:0] $end
$scope begin booth_stage[0] $end
$scope module u_booth $end
$var wire 3 -# booth_group [2:0] $end
$var wire 4 .# group_index [3:0] $end
$var wire 8 /# multiplicand [7:0] $end
$var reg 16 0# partial_product_out [15:0] $end
$var reg 16 1# unshifted_pp [15:0] $end
$upscope $end
$upscope $end
$scope begin booth_stage[1] $end
$scope module u_booth $end
$var wire 3 2# booth_group [2:0] $end
$var wire 4 3# group_index [3:0] $end
$var wire 8 4# multiplicand [7:0] $end
$var reg 16 5# partial_product_out [15:0] $end
$var reg 16 6# unshifted_pp [15:0] $end
$upscope $end
$upscope $end
$scope begin booth_stage[2] $end
$scope module u_booth $end
$var wire 3 7# booth_group [2:0] $end
$var wire 4 8# group_index [3:0] $end
$var wire 8 9# multiplicand [7:0] $end
$var reg 16 :# partial_product_out [15:0] $end
$var reg 16 ;# unshifted_pp [15:0] $end
$upscope $end
$upscope $end
$scope begin booth_stage[3] $end
$scope module u_booth $end
$var wire 3 <# booth_group [2:0] $end
$var wire 4 =# group_index [3:0] $end
$var wire 8 ># multiplicand [7:0] $end
$var reg 16 ?# partial_product_out [15:0] $end
$var reg 16 @# unshifted_pp [15:0] $end
$upscope $end
$upscope $end
$upscope $end
$upscope $end
$upscope $end
$enddefinitions $end
#0
$dumpvars
b0 @#
b0 ?#
b0 >#
b11 =#
b0 <#
b0 ;#
b0 :#
b0 9#
b10 8#
b0 7#
b0 6#
b0 5#
b0 4#
b1 3#
b0 2#
b0 1#
b0 0#
b0 /#
b0 .#
b0 -#
b0 ,#
b0 +#
b0 *#
b0 )#
0(#
0'#
0&#
0%#
0$#
0##
0"#
0!#
0~"
0}"
0|"
0{"
0z"
0y"
0x"
0w"
0v"
0u"
0t"
0s"
0r"
0q"
0p"
0o"
0n"
0m"
0l"
0k"
0j"
0i"
0h"
0g"
0f"
0e"
0d"
0c"
0b"
0a"
0`"
0_"
0^"
0]"
0\"
0["
0Z"
0Y"
0X"
0W"
0V"
0U"
0T"
0S"
0R"
0Q"
0P"
0O"
0N"
0M"
0L"
0K"
0J"
0I"
0H"
0G"
0F"
0E"
0D"
0C"
0B"
0A"
0@"
0?"
0>"
0="
0<"
0;"
0:"
09"
08"
07"
b0 6"
b0 5"
b0 4"
b0 3"
b0 2"
01"
00"
0/"
0."
0-"
0,"
0+"
0*"
0)"
0("
0'"
0&"
0%"
0$"
0#"
0""
0!"
0~
0}
0|
0{
0z
0y
0x
0w
0v
0u
0t
0s
0r
0q
0p
0o
0n
0m
0l
0k
0j
0i
0h
0g
0f
0e
0d
0c
0b
0a
0`
0_
0^
0]
0\
0[
0Z
0Y
0X
0W
0V
0U
0T
0S
0R
0Q
0P
0O
0N
0M
0L
0K
0J
0I
0H
0G
0F
0E
0D
0C
0B
0A
0@
b0 ?
b0 >
b0 =
b0 <
b0 ;
b0 :
b0 9
b0 8
b0 7
b0 6
b0 5
b0 4
b0 3
b0 2
b0 1
b0 0
b0 /
b0 .
b0 -
b0 ,
b0 +
b0 *
b0 )
bx (
1'
0&
0%
b0 $
b0 #
b0 "
0!
$end
#5000
1%
#10000
0%
#15000
1%
#20000
0%
b10100 $
b10100 *
b110010 #
b110010 )
1&
0'
#25000
b1100100000 :#
b110010 ;#
b110010000000000000110010000000000000000000 0
b110010000000000000110010000000000000000000 +#
b11001000 5#
b110010 6#
b10 7#
b10 2#
1!
b101000 ,#
b10100 3
b10100 *#
b110010 2
b110010 )#
b110010 /#
b110010 4#
b110010 9#
b110010 >#
1%
#30000
0%
#35000
1S
1b
1g
1]
1l
b1111101000 .
b1111101000 >
1q
1P
1_
1d
1[
1j
1o
b11001000 <
b1100100000 =
b110010000000000000110010000000000000000000 5
1%
#40000
0%
b1100 $
b1100 *
b11110110 #
b11110110 )
#45000
1J"
1T"
1Y"
1^"
1c"
b1111101000 ,
b1111101000 5"
1h"
1F"
1P"
1U"
1Z"
1_"
1d"
b1 7#
b110 2#
b101000 5#
b1010 6#
b111111110110000000000000001010000000000000000000 0
b111111110110000000000000001010000000000000000000 +#
b1111111101100000 :#
b1111111111110110 ;#
b1111101000 8
b1111101000 2"
b11000 ,#
b1100 3
b1100 *#
b11110110 2
b11110110 )#
b11110110 /#
b11110110 4#
b11110110 9#
b11110110 >#
1%
#50000
0%
#55000
0]
b100000 /
b100000 ?
1\
0g
1b
1v
1{
1""
1'"
1,"
b1111111101001000 .
b1111111101001000 >
11"
1Z
0_
0d
1`
1t
1y
1~
1%"
1*"
1/"
b101000 <
b1111111101100000 =
b111111110110000000000000001010000000000000000000 5
b1111101000 1
b1111101000 :
1%
#60000
0%
b11111011 $
b11111011 *
b1100100 #
b1100100 )
#65000
b1000000 -
b1000000 6"
1X"
0Y"
0T"
0^"
1m"
1r"
1w"
1|"
1##
b1111111100001000 ,
b1111111100001000 5"
1(#
1V"
b1111111110011100 0#
b1111111110011100 1#
b1000000 3"
0P"
0Z"
1i"
1n"
1s"
1x"
1}"
1$#
b111 <#
b111 7#
b101 2#
b110 -#
b1111111001110000 5#
b1111111110011100 6#
b11111110011100001111111110011100 0
b11111110011100001111111110011100 +#
b0 :#
b0 ;#
b1111101000 "
b1111101000 4
b100000 6
b1111111101001000 8
b1111111101001000 2"
b1111110110 ,#
b11111011 3
b11111011 *#
b1100100 2
b1100100 )#
b1100100 /#
b1100100 4#
b1100100 9#
b1100100 >#
1%
#70000
0%
#75000
1W
1p
1u
1z
1!"
1&"
1+"
10"
1N
1g
b1111111000010000 /
b1111111000010000 ?
0\
1]
1b
1l
0q
0v
0{
0""
0'"
0,"
b111101100 .
b111101100 >
01"
1J
1O
1T
1c
1h
1m
1r
1w
1|
1#"
1("
1-"
0P
1U
1_
1n
1s
1x
1}
1$"
1)"
1."
0[
0`
0j
0o
0t
0y
0~
0%"
0*"
0/"
b1111111110011100 ;
b1111111001110000 <
b0 =
b11111110011100001111111110011100 5
b1000000 9
b1111111110001000 1
b1111111100001000 :
1%
#80000
0%
b11111111 $
b11111111 *
b10000000 #
b10000000 )
#85000
1S"
b100000 -
b100000 6"
0X"
1Y"
1E"
0T"
1^"
0h"
1m"
1r"
1w"
1|"
1##
b1111110111001100 ,
b1111110111001100 5"
1(#
1Q"
0V"
1j"
1o"
1t"
1y"
1~"
1%#
b1111110000100000 3"
1A"
1P"
1Z"
0d"
0i"
0n"
0s"
0x"
0}"
0$#
b111 2#
b10000000 0#
b10000000 1#
b10000000 0
b10000000 +#
b0 5#
b0 6#
b1111111110001000 "
b1111111110001000 4
b1111111000010000 6
b111101100 8
b111101100 2"
b1111111110 ,#
b11111111 3
b11111111 *#
b10000000 2
b10000000 )#
b10000000 /#
b10000000 4#
b10000000 9#
b10000000 >#
1%
#90000
0%
#95000
0W
0p
0u
0z
0!"
0&"
0+"
b0 /
b0 ?
00"
0N
0S
0l
0]
b10000000 .
b10000000 >
0b
0J
0O
0T
0h
0m
0r
0w
0|
0#"
0("
0-"
0U
0Z
0_
0n
0s
0x
0}
0$"
0)"
0."
b10000000 ;
b0 <
b10000000 5
b100000 9
b1111111000001100 1
b1111110111001100 :
1%
#100000
0%
b1111111 $
b1111111 *
b1111111 #
b1111111 )
#105000
0m"
0r"
0w"
0|"
0##
0(#
b0 -
b0 6"
0S"
0E"
0J"
0T"
0Y"
b10000000 ,
b10000000 5"
0c"
0Q"
0j"
0o"
0t"
0y"
0~"
0%#
b11111110000000 ?#
b11111110 @#
b0 3"
0A"
0F"
0P"
0U"
0_"
b11 <#
b11111110000000000000000000000000000000000000001111111110000001 0
b11111110000000000000000000000000000000000000001111111110000001 +#
b1111111110000001 0#
b1111111110000001 1#
b1111111000001100 "
b1111111000001100 4
b0 6
b10000000 8
b10000000 2"
b11111110 ,#
b1111111 3
b1111111 *#
b1111111 2
b1111111 )#
b1111111 /#
b1111111 4#
b1111111 9#
b1111111 >#
1%
#110000
0%
#115000
1D
1l
1q
1v
1{
1""
1'"
1,"
b1111111110000001 .
b1111111110000001 >
11"
1@
1h
1m
1r
1w
1|
1#"
1("
1-"
b1111111110000001 ;
b11111110000000 +
b11111110000000000000000000000000000000000000001111111110000001 5
b0 9
b10000000 1
b10000000 :
1%
#120000
0%
b10000001 $
b10000001 *
b100100 #
b100100 )
b0 (
#125000
1]"
1b"
1g"
1l"
1q"
1v"
b11111110000000 -
b11111110000000 6"
1{"
1;"
1##
1(#
b1100000000000001 ,
b1100000000000001 5"
0^"
1\"
1a"
1f"
1k"
1p"
1u"
1z"
17"
1_"
1d"
1i"
1n"
1s"
1x"
1}"
1$#
b100 <#
b0 7#
b0 2#
b10 -#
b100100 0#
b100100 1#
b1110111000000000000000000000000000000000000000000000000000100100 0
b1110111000000000000000000000000000000000000000000000000000100100 +#
b1110111000000000 ?#
b1111111110111000 @#
b10000000 "
b10000000 4
b11111110000000 7
b11111110000000 4"
b1111111110000001 8
b1111111110000001 2"
b1100000010 ,#
b10000001 3
b10000001 *#
b100100 2
b100100 )#
b100100 /#
b100100 4#
b100100 9#
b100100 >#
1%
#130000
0%
#135000
0D
1N
1]
0g
0l
0q
0v
0{
0""
0'"
0,"
b100100 .
b100100 >
01"
0@
1J
1Y
0c
0h
0m
0r
0w
0|
0#"
0("
0-"
b100100 ;
b1110111000000000 +
b1110111000000000000000000000000000000000000000000000000000100100 5
b11111110000000 9
b11111100000001 1
b1100000000000001 :
1%
#140000
0%
b1100011 $
b1100011 *
b1001 #
b1001 )
b1 (
#145000
0]"
0b"
0g"
0l"
0q"
0v"
b0 -
b0 6"
0{"
0;"
1E"
1T"
1h"
1m"
1r"
b1110111000100100 ,
b1110111000100100 5"
1|"
b1111111011100000 :#
b1111111111101110 ;#
b100100 5#
b1001 6#
0\"
0a"
0u"
1!#
1&#
07"
1A"
1P"
0Z"
0_"
0d"
0i"
0n"
0s"
0x"
0}"
0$#
b11 <#
b100 7#
b1 2#
b110 -#
b1111111111110111 0#
b1111111111110111 1#
b10010000000111111101110000000000000001001001111111111110111 0
b10010000000111111101110000000000000001001001111111111110111 +#
b10010000000 ?#
b10010 @#
b11111100000001 "
b11111100000001 4
b1110111000000000 7
b1110111000000000 4"
b100100 8
b100100 2"
b11000110 ,#
b1100011 3
b1100011 *#
b1001 2
b1001 )#
b1001 /#
b1001 4#
b1001 9#
b1001 >#
1%
#150000
0%
#155000
1M
1a
1f
1p
1u
1z
1!"
1&"
1+"
10"
1D
1I
1X
1l
0N
b1111111011100100 /
b1111111011100100 ?
1\
1]
0b
0g
0q
0v
0{
0""
0'"
0,"
b100110011 .
b100110011 >
01"
1@
1E
1T
1^
1c
1h
1m
1r
1w
1|
1#"
1("
1-"
1K
1Z
1[
1`
1e
1o
1t
1y
1~
1%"
1*"
1/"
b1111111111110111 ;
b100100 <
b1111111011100000 =
b10010000000 +
b10010000000111111101110000000000000001001001111111111110111 5
b0 9
b1110111000100100 1
b1110111000100100 :
1%
#160000
0%
b10001101 $
b10001101 *
b1101 #
b1101 )
b10 (
#165000
1b"
1J"
1Y"
0m"
1l"
1w"
b10110000000 -
b10110000000 6"
1]"
1;"
1@"
0E"
1O"
0c"
0^"
0h"
1r"
1|"
1##
b1111100001111011 ,
b1111100001111011 5"
1(#
1G"
1V"
1["
1`"
1j"
1o"
1t"
1y"
1~"
1%#
1\"
0f"
0p"
0z"
0!#
0&#
b1111110111001000 3"
17"
1<"
0A"
1K"
1_"
b100 <#
b1 7#
b110 2#
b10 -#
b1101 0#
b1101 1#
b1111111111001100 5#
b1111111111110011 6#
b11010000 :#
b1101 ;#
b1111100110000000000000001101000011111111110011000000000000001101 0
b1111100110000000000000001101000011111111110011000000000000001101 +#
b1111100110000000 ?#
b1111111111100110 @#
b1110111000100100 "
b1110111000100100 4
b10010000000 7
b10010000000 4"
b1111111011100100 6
b100110011 8
b100110011 2"
b1100011010 ,#
b10001101 3
b10001101 *#
b1101 2
b1101 )#
b1101 /#
b1101 4#
b1101 9#
b1101 >#
1%
#170000
0%
#175000
1R
0\
0p
0u
0z
0!"
0&"
0+"
b11001100 /
b11001100 ?
00"
0I
1X
0]
1q
1v
1{
1""
1'"
1,"
b1111111100010001 .
b1111111100010001 >
11"
0E
1O
0T
0Y
0^
0c
0h
0m
0r
0w
0|
0#"
0("
0-"
1P
0Z
1_
1d
1i
1n
1s
1x
1}
1$"
1)"
1."
1V
0[
0o
0t
0y
0~
0%"
0*"
0/"
b1101 ;
b1111111111001100 <
b11010000 =
b1111100110000000 +
b1111100110000000000000001101000011111111110011000000000000001101 5
b10110000000 9
b1101111011 1
b1111100001111011 :
1%
#180000
0%
b10010 $
b10010 *
b1100101 #
b1100101 )
b11 (
#185000
1N"
0l"
0O"
0Y"
1m"
0r"
0w"
0|"
0##
0(#
1q"
1v"
1{"
1"#
b1111100110010000 -
b1111100110010000 6"
1'#
0@"
0T"
1h"
b11100001001 ,
b11100001001 5"
1c"
1L"
0V"
0j"
0o"
0t"
0y"
0~"
0%#
1a"
0k"
1p"
1u"
1z"
1!#
1&#
b110011000 3"
0<"
0P"
1d"
1i"
1n"
1s"
1x"
1}"
1$#
b0 <#
b10 7#
b1 2#
b100 -#
b1111111100110110 0#
b1111111100110110 1#
b110010100 5#
b1100101 6#
b11001010000 :#
b1100101 ;#
b1100101000000000001100101001111111100110110 0
b1100101000000000001100101001111111100110110 +#
b0 ?#
b0 @#
b1101111011 "
b1101111011 4
b1111100110000000 7
b1111100110000000 4"
b11001100 6
b1111111100010001 8
b1111111100010001 2"
b100100 ,#
b10010 3
b10010 *#
b1100101 2
b1100101 )#
b1100101 /#
b1100101 4#
b1100101 9#
b1100101 >#
1%
#190000
0%
#195000
1k
0R
1p
1u
0D
1I
1]
0l
1W
1b
0a
b11100010100 /
b11100010100 ?
0f
1g
0q
b1111100011110010 .
b1111100011110010 >
0v
0@
1E
0O
1T
1Y
1h
1m
1r
1w
1|
1#"
1("
1-"
0P
1U
0_
0n
0s
0x
0}
0$"
0)"
0."
0e
1o
1t
b1111111100110110 ;
b110010100 <
b11001010000 =
b0 +
b1100101000000000001100101001111111100110110 5
b1111100110010000 9
b1111101000101001 1
b11100001001 :
1%
#200000
0%
b1101 $
b1101 *
b1 #
b1 )
b100 (
